shapes_overlay/__init__.py
shapes_overlay-0.1.0.dist-info/METADATA
shapes_overlay-0.1.0.dist-info/WHEEL
shapes_overlay-0.1.0.dist-info/entry_points.txt
shapes_overlay-0.1.0.dist-info/top_level.txt
shapes_overlay-0.1.0.dist-info/RECORD
