Metadata-Version: 2.4
Name: shapes-overlay
Version: 0.1.0
Summary: Operações espaciais entre shapefiles com GeoPandas overlay
Author-email: Ricardo Malnati <ricardomalnati@gmail.com>
License-Expression: MIT
Requires-Python: >=3.10
Requires-Dist: geopandas
Requires-Dist: shapely
Requires-Dist: fiona
Requires-Dist: pyproj
